strawberry_wagtail/__init__.py
strawberry_wagtail/apps.py
strawberry_wagtail/py.typed
strawberry_wagtail/scalars.py
strawberry_wagtail/schema.py
strawberry_wagtail/stream_field.py
strawberry_wagtail/views.py
strawberry_wagtail-0.1.0.dist-info/LICENSE
strawberry_wagtail-0.1.0.dist-info/WHEEL
strawberry_wagtail-0.1.0.dist-info/METADATA
strawberry_wagtail-0.1.0.dist-info/RECORD
