Metadata-Version: 2.1
Name: strawberry-wagtail
Version: 0.1.0
Summary: 
License: MIT
Author: Patrick Arminio
Author-email: patrick.arminio@gmail.com
Requires-Python: >=3.7,<4.0
Classifier: License :: OSI Approved :: MIT License
Classifier: Programming Language :: Python :: 3
Classifier: Programming Language :: Python :: 3.10
Classifier: Programming Language :: Python :: 3.7
Classifier: Programming Language :: Python :: 3.8
Classifier: Programming Language :: Python :: 3.9
Requires-Dist: strawberry-graphql (>=0.103.1,<0.104.0)
Requires-Dist: strawberry-graphql-django (>=0.2.5,<0.3.0)
